heavylight/__init__.py
heavylight/heavylight.py
heavylight/heavytables.py
heavylight/make_examples.py
heavylight/memory_optimized_cache.py
heavylight/memory_optimized_model.py
heavylight/examples/protection/protection_model_base.py
heavylight/examples/protection/protection_model_mo.py
heavylight/examples/protection/protection_model_np.py
heavylight/examples/protection/protection_risk_model_generic.xlsx
heavylight/examples/protection/readme.md
heavylight/examples/protection/run_model_base.py
heavylight/examples/protection/run_model_mo.py
heavylight/examples/protection/run_model_np.py
heavylight/examples/protection/tables/forward_rates.csv
heavylight/examples/protection/tables/q_x_generic.csv
heavylight/examples/template/model.py
heavylight-1.0.10.dist-info/METADATA
heavylight-1.0.10.dist-info/WHEEL
heavylight-1.0.10.dist-info/licenses/LICENSE
heavylight-1.0.10.dist-info/RECORD
