Metadata-Version: 2.4
Name: heavylight
Version: 1.0.10
Summary: Heavylight Actuarial Modelling Framework
Project-URL: Homepage, https://github.com/lewisfogden/heavylight/
Project-URL: Bug Tracker, https://github.com/lewisfogden/heavylight/issues
Project-URL: Documentation, https://lewisfogden.github.io/heavylight/
Author-email: Lewis Fogden <lewisfogden@gmail.com>, Matthew Caseres <matthewcaseres@outlook.com>
License-File: LICENSE
Classifier: License :: OSI Approved :: MIT License
Classifier: Operating System :: OS Independent
Classifier: Programming Language :: Python :: 3
Requires-Python: >=3.8
Requires-Dist: pandas>=1.2
Provides-Extra: dev
Requires-Dist: numpy; extra == 'dev'
Requires-Dist: pytest-cov; extra == 'dev'
Requires-Dist: pytest-timeout; extra == 'dev'
Requires-Dist: pytest==7.4.3; extra == 'dev'
Provides-Extra: docs
Requires-Dist: mkdocs; extra == 'docs'
Requires-Dist: mkdocs-jupyter; extra == 'docs'
Requires-Dist: mkdocs-material; extra == 'docs'
Requires-Dist: mkdocstrings[python]; extra == 'docs'
